{
  "resourceType": "StructureDefinition",
  "id": "CodeSystemVersionReference",
  "url": "{http://www.omg.org/spec/CTS2/1.1/Core}CodeSystemVersionReference",
  "name": "CodeSystemVersionReference",
  "display": "CTS2.CodeSystemVersionReference",
  "status": "draft",
  "publisher": "Generated by Xsd-to-FHIR",
  "contact": [
    {
      "name": "Visit the Github repository for more information",
      "telecom": [
        {
          "system": "other",
          "value": "https://github.com/cts2/CTS2-to-FHIR"
        }
      ]
    }
  ],
  "date": "2016-02-08T19:11:02-07:00",
  "description": "a reference to a specific version of code system and, if known, the code system which it is a version of",
  "fhirVersion": "1.4.0",
  "kind": "logical",
  "abstract": false,
  "snapshot": {
    "element": [
      {
        "path": "CodeSystemVersionReference",
        "short": "CodeSystemVersionReference",
        "definition": "a reference to a specific version of code system and, if known, the code system which it is a version of",
        "min": 0,
        "max": "*"
      },
      {
        "path": "CodeSystemVersionReference.version",
        "name": "version",
        "short": "TODO: Description",
        "definition": "TODO: Description",
        "min": 1,
        "max": "1",
        "type": [
          {
            "code": "NameAndMeaningReference"
          }
        ]
      },
      {
        "path": "CodeSystemVersionReference.codeSystem",
        "name": "codeSystem",
        "short": "A reference to the code system that the version is a version of",
        "definition": "A reference to the code system that the version is a version of. Must be present if this information is known to the CTS2 service implementation.",
        "min": 0,
        "max": "1",
        "type": [
          {
            "code": "CodeSystemReference"
          }
        ]
      }
    ]
  }
}